{
    "city": {
        "lang": "en",
        "cityName": "Corryong",
        "cityLatitude": "-36.180000000",
        "cityLongitude": "147.890000000",
        "cityId": 1666,
        "isCapital": false,
        "stationName": "Corryong",
        "tourismURL": "",
        "tourismBoardName": "",
        "isDep": false,
        "timeZone": "+1000",
        "isDST": "N",
        "member": {
            "memId": 185,
            "memName": "Australia",
            "shortMemName": "",
            "url": "www.bom.gov.au",
            "orgName": "Bureau of Meteorology",
            "logo": "australia_logo.png",
            "ra": 5
        },
        "forecast": {
            "issueDate": "2026-04-10 04:00:00",
            "timeZone": "Local",
            "forecastDay": [
                {
                    "forecastDate": "2026-04-13",
                    "wxdesc": "",
                    "weather": "Cloudy",
                    "minTemp": "2",
                    "maxTemp": "17",
                    "minTempF": "36",
                    "maxTempF": "63",
                    "weatherIcon": 2301
                },
                {
                    "forecastDate": "2026-04-14",
                    "wxdesc": "",
                    "weather": "Partly Cloudy",
                    "minTemp": "5",
                    "maxTemp": "20",
                    "minTempF": "41",
                    "maxTempF": "68",
                    "weatherIcon": 2202
                },
                {
                    "forecastDate": "2026-04-15",
                    "wxdesc": "",
                    "weather": "Partly Cloudy",
                    "minTemp": "4",
                    "maxTemp": "21",
                    "minTempF": "39",
                    "maxTempF": "70",
                    "weatherIcon": 2202
                },
                {
                    "forecastDate": "2026-04-16",
                    "wxdesc": "",
                    "weather": "Partly Cloudy",
                    "minTemp": "4",
                    "maxTemp": "21",
                    "minTempF": "39",
                    "maxTempF": "70",
                    "weatherIcon": 2202
                },
                {
                    "forecastDate": "2026-04-17",
                    "wxdesc": "",
                    "weather": "Partly Cloudy",
                    "minTemp": "7",
                    "maxTemp": "20",
                    "minTempF": "45",
                    "maxTempF": "68",
                    "weatherIcon": 2202
                }
            ]
        },
        "climate": {
            "raintype": "N/A",
            "raindef": "",
            "rainunit": "",
            "datab": "",
            "datae": "",
            "tempb": "",
            "tempe": "",
            "rdayb": "",
            "rdaye": "",
            "rainfallb": "",
            "rainfalle": "",
            "climatefromclino": "",
            "climateMonth": []
        }
    }
}