{
    "city": {
        "lang": "en",
        "cityName": "Kab. Padanglawas Utara",
        "cityLatitude": "1.506327000",
        "cityLongitude": "99.624710000",
        "cityId": 3307,
        "isCapital": false,
        "stationName": "Kab. Padanglawas Utara",
        "tourismURL": "",
        "tourismBoardName": "",
        "isDep": false,
        "timeZone": "+0700",
        "isDST": "N",
        "member": {
            "memId": 43,
            "memName": "Indonesia",
            "shortMemName": "",
            "url": "www.bmkg.go.id",
            "orgName": "Meteorological, Climatological and Geophysical Agency (BMKG)",
            "logo": "indonesia_logo.png",
            "ra": 5
        },
        "forecast": {
            "issueDate": "N/A",
            "timeZone": "N/A",
            "forecastDay": []
        },
        "climate": {
            "raintype": "N/A",
            "raindef": "",
            "rainunit": "",
            "datab": "",
            "datae": "",
            "tempb": "",
            "tempe": "",
            "rdayb": "",
            "rdaye": "",
            "rainfallb": "",
            "rainfalle": "",
            "climatefromclino": "",
            "climateMonth": []
        }
    }
}